MannKS/__init__.py
MannKS/_ats.py
MannKS/_autocorr.py
MannKS/_bootstrap.py
MannKS/_datetime.py
MannKS/_helpers.py
MannKS/_large_dataset.py
MannKS/_segmented.py
MannKS/_stats.py
MannKS/analysis_notes.py
MannKS/check_seasonality.py
MannKS/classification.py
MannKS/inspection.py
MannKS/plotting.py
MannKS/preprocessing.py
MannKS/regional_test.py
MannKS/rolling_trend.py
MannKS/seasonal_trend_test.py
MannKS/segmented_trend_test.py
MannKS/trend_test.py
mannks-0.5.0.dist-info/LICENSE
mannks-0.5.0.dist-info/METADATA
mannks-0.5.0.dist-info/WHEEL
mannks-0.5.0.dist-info/RECORD
