Metadata-Version: 2.1
Name: mannks
Version: 0.5.0
Summary: Non-parametric trend analysis for unequally spaced time series with censored data and large dataset support
Home-page: https://github.com/LukeAFullard/MannKS
License: MIT
Keywords: mann-kendall,sen-slope,trend-analysis,censored-data,time-series,segmented-regression,piecewise-regression,breakpoint-detection,rolling-trend,bootstrap
Author: Luke Fullard
Requires-Python: >=3.7
Classifier: License :: OSI Approved :: MIT License
Classifier: Programming Language :: Python :: 3
Classifier: Programming Language :: Python :: 3.7
Classifier: Programming Language :: Python :: 3.8
Classifier: Programming Language :: Python :: 3.9
Classifier: Programming Language :: Python :: 3.10
Classifier: Programming Language :: Python :: 3.11
Classifier: Programming Language :: Python :: 3.12
Requires-Dist: matplotlib (>=3.3.0)
Requires-Dist: numpy (>=1.19.0)
Requires-Dist: pandas (>=1.1.0)
Requires-Dist: piecewise-regression (>=1.5.0,<2.0.0)
Requires-Dist: scipy (>=1.5.0)
Requires-Dist: seaborn (>=0.11.0)
Project-URL: Documentation, https://github.com/LukeAFullard/MannKS/tree/main/Examples
Project-URL: Repository, https://github.com/LukeAFullard/MannKS
